aif_agent_builder_sdk/__init__.py
aif_agent_builder_sdk/client.py
aif_agent_builder_sdk/exceptions.py
aif_agent_builder_sdk/models.py
aif_agent_builder_sdk/token_verifier.py
examples/basic_usage.py
heimdall_agent_builder_sdk-0.2.0.dist-info/licenses/LICENSE
tests/__init__.py
tests/conftest.py
tests/test_client.py
tests/test_integration.py
heimdall_agent_builder_sdk-0.2.0.dist-info/METADATA
heimdall_agent_builder_sdk-0.2.0.dist-info/WHEEL
heimdall_agent_builder_sdk-0.2.0.dist-info/top_level.txt
heimdall_agent_builder_sdk-0.2.0.dist-info/RECORD
