Metadata-Version: 2.4
Name: heimdall-agent-builder-sdk
Version: 0.2.0
Summary: Python SDK for Agent Builders to interact with Heimdall AIF Core Service. Install: 'pip install heimdall-agent-builder-sdk', Import: 'from aif_agent_builder_sdk import AIFClient'
Author-email: IAM Heimdall Team <contact@iamheimdall.com>
License: MIT License
Project-URL: Homepage, https://iamheimdall.com
Project-URL: Documentation, https://github.com/IAM-Heimdall/heimdall_agent_builder_sdk_python#readme
Project-URL: Repository, https://github.com/IAM-Heimdall/heimdall_agent_builder_sdk_python
Project-URL: Bug Tracker, https://github.com/IAM-Heimdall/heimdall_agent_builder_sdk_python/issues
Keywords: aif,agent,identity,sdk,jwt,token,heimdall,agent-builder
Classifier: Development Status :: 4 - Beta
Classifier: Intended Audience :: Developers
Classifier: License :: OSI Approved :: MIT License
Classifier: Operating System :: OS Independent
Classifier: Programming Language :: Python :: 3
Classifier: Programming Language :: Python :: 3.8
Classifier: Programming Language :: Python :: 3.9
Classifier: Programming Language :: Python :: 3.10
Classifier: Programming Language :: Python :: 3.11
Classifier: Programming Language :: Python :: 3.12
Classifier: Topic :: Software Development :: Libraries :: Python Modules
Classifier: Topic :: Security
Classifier: Topic :: Internet :: WWW/HTTP
Requires-Python: >=3.8
License-File: LICENSE
Requires-Dist: pydantic<3.0.0,>=2.0.0
Requires-Dist: httpx<1.0.0,>=0.25.0
Requires-Dist: python-dotenv>=1.0.0
Requires-Dist: PyJWT>=2.8.0
Requires-Dist: cryptography>=41.0.0
Provides-Extra: test
Requires-Dist: pytest>=7.0.0; extra == "test"
Requires-Dist: pytest-asyncio>=0.18.0; extra == "test"
Requires-Dist: pytest-httpx>=0.20.0; extra == "test"
Requires-Dist: respx>=0.20.0; extra == "test"
Requires-Dist: pytest-cov>=4.0.0; extra == "test"
Provides-Extra: dev
Requires-Dist: heimdall-agent-builder-sdk[test]; extra == "dev"
Requires-Dist: black>=22.0.0; extra == "dev"
Requires-Dist: flake8>=4.0.0; extra == "dev"
Requires-Dist: mypy>=1.0.0; extra == "dev"
Requires-Dist: types-requests; extra == "dev"
Requires-Dist: bump-my-version>=0.10.0; extra == "dev"
Dynamic: license-file
